nonetrip/__init__.py
nonetrip/argparse.py
nonetrip/command/__init__.py
nonetrip/command/argfilter/__init__.py
nonetrip/command/argfilter/controllers.py
nonetrip/command/argfilter/converters.py
nonetrip/command/argfilter/extractors.py
nonetrip/command/argfilter/validators.py
nonetrip/command/group.py
nonetrip/command/group.pyi
nonetrip/compat/__init__.py
nonetrip/compat/bus.py
nonetrip/compat/config.py
nonetrip/compat/exceptions.py
nonetrip/compat/message.py
nonetrip/compat/poly.py
nonetrip/default_config.py
nonetrip/exceptions.py
nonetrip/experimental/__init__.py
nonetrip/experimental/permission.py
nonetrip/experimental/plugin.py
nonetrip/helpers.py
nonetrip/log.py
nonetrip/message.py
nonetrip/natural_language.py
nonetrip/notice_request.py
nonetrip/permission.py
nonetrip/plugin.py
nonetrip/plugins/__init__.py
nonetrip/plugins/base.py
nonetrip/py.typed
nonetrip/sched.py
nonetrip/session.py
nonetrip/typing.py
nonetrip-0.3.4.dist-info/LICENSE
nonetrip-0.3.4.dist-info/WHEEL
nonetrip-0.3.4.dist-info/METADATA
nonetrip-0.3.4.dist-info/RECORD
